crumby
